flwr_serverless/__init__.py
flwr_serverless/version.py
flwr_serverless/federated_node/__init__.py
flwr_serverless/federated_node/aggregatable.py
flwr_serverless/federated_node/async_federated_node.py
flwr_serverless/federated_node/sync_federated_node.py
flwr_serverless/keras/__init__.py
flwr_serverless/keras/example.py
flwr_serverless/keras/federated_learning_callback.py
flwr_serverless/shared_folder/__init__.py
flwr_serverless/shared_folder/base_folder.py
flwr_serverless/shared_folder/in_memory_folder.py
flwr_serverless/shared_folder/local_folder.py
flwr_serverless/shared_folder/s3_folder.py
tests/__init__.py
tests/test_flwr_base.py
tests/test_s3_folder.py
tests/test_tf_training.py
tests/experiments/__init__.py
tests/experiments/test_keras_models.py
tests/shared_folder/__init__.py
tests/shared_folder/test_s3_folder.py
flwr_serverless-0.2.10.dist-info/METADATA
flwr_serverless-0.2.10.dist-info/WHEEL
flwr_serverless-0.2.10.dist-info/top_level.txt
flwr_serverless-0.2.10.dist-info/RECORD
