Metadata-Version: 2.1
Name: flwr_serverless
Version: 0.2.10
Summary: A serverless federated learning library based on flwr
Home-page: https://github.com/kungfuai/flwr_serverless
Author: Kungfu AI
Author-email: zhangzhang.si@gmail.com
License: MIT
Requires-Python: >=3.6
Requires-Dist: flwr <1.7
Requires-Dist: python-dotenv
